LICENSE.txt
MANIFEST.in
NEWS.rst
README.rst
setup.py
DeeFuzzer.egg-info/PKG-INFO
DeeFuzzer.egg-info/SOURCES.txt
DeeFuzzer.egg-info/dependency_links.txt
DeeFuzzer.egg-info/not-zip-safe
DeeFuzzer.egg-info/requires.txt
DeeFuzzer.egg-info/top_level.txt
deefuzzer/__init__.py
deefuzzer/core.py
deefuzzer/player.py
deefuzzer/recorder.py
deefuzzer/relay.py
deefuzzer/station.py
deefuzzer/streamer.py
deefuzzer/tools/PyRSS2Gen.py
deefuzzer/tools/__init__.py
deefuzzer/tools/get_access_token.py
deefuzzer/tools/logger.py
deefuzzer/tools/mediabase.py
deefuzzer/tools/mp3.py
deefuzzer/tools/ogg.py
deefuzzer/tools/osc.py
deefuzzer/tools/streamer.py
deefuzzer/tools/twitt.py
deefuzzer/tools/utils.py
deefuzzer/tools/webm.py
deefuzzer/tools/xml2yaml.py
deefuzzer/tools/xmltodict.py
deefuzzer/tools/xmltodict2.py
deefuzzer/tools/xmltodict3.py
doc/img/logo_deefuzzer.png
doc/img/logo_deefuzzer_notxt.png
doc/img/logo_deefuzzer_wh.png
example/deefuzzer.json
example/deefuzzer.xml
example/deefuzzer.yaml
example/deefuzzer_doc.xml
example/deefuzzer_multiple.yaml
example/deefuzzer_telecaster_test.yaml
example/deefuzzer_test.xml
example/deefuzzer_webm.json
example/deefuzzer_webm_file.json
example/deefuzzer_webm_relay.json
example/deefuzzer_webm_relay_multiple.yaml
example/stationconfig_doc.xml
scripts/deefuzzer
scripts/dev/make_doc.sh
scripts/dev/pypi.sh
scripts/dev/xml2yaml.py
scripts/etc/default/deefuzzer
scripts/etc/init.d/deefuzzer
scripts/osc/osc_jingles_start.py
scripts/osc/osc_jingles_stop.py
scripts/osc/osc_player_fast.py
scripts/osc/osc_player_next.py
scripts/osc/osc_player_slow.py
scripts/osc/osc_record_start.py
scripts/osc/osc_record_stop.py
scripts/osc/osc_relay_start.py
scripts/osc/osc_relay_stop.py
scripts/osc/osc_twitter_start.py
scripts/osc/osc_twitter_stop.py