Metadata-Version: 2.1
Name: DeeFuzzer
Version: 0.9.0
Summary: open, light and instant media streaming tool
Home-page: http://github.com/yomguy/DeeFuzzer
Author: Guillaume Pellerin
Author-email: yomguy@parisson.com
License: GPL v3
Platform: OS Independent
Classifier: Programming Language :: Python :: 3
Classifier: Programming Language :: Python :: 3.11
Classifier: Topic :: Internet :: WWW/HTTP :: Dynamic Content
Classifier: Topic :: Multimedia :: Sound/Audio
Classifier: Topic :: Multimedia :: Sound/Audio :: Players
Classifier: License :: OSI Approved :: GNU General Public License v3 (GPLv3)
Requires-Python: >=3
License-File: LICENSE.txt
